ntupledicts/__init__.py
ntupledicts/analyze.py
ntupledicts/load.py
ntupledicts/operations.py
ntupledicts/plot.py
ntupledicts/ml/__init__.py
ntupledicts/ml/data.py
ntupledicts/ml/models.py
ntupledicts/ml/plot.py
ntupledicts/ml/predict.py
ntupledicts-0.9.3.dist-info/LICENSE
ntupledicts-0.9.3.dist-info/METADATA
ntupledicts-0.9.3.dist-info/WHEEL
ntupledicts-0.9.3.dist-info/top_level.txt
ntupledicts-0.9.3.dist-info/RECORD
