Metadata-Version: 2.1
Name: ntupledicts
Version: 0.9.3
Summary: Treating CMS TrackTrigger ROOT Ntuples as Python dictionaries with ML studies in mind.
Home-page: https://github.com/cqpancoast/ntupledicts
Author: Casey Pancoast
Author-email: cqpancoast@gmail.com
License: MIT
Keywords: cms tracktrigger track-trigger root ntuple python dictionary dict ml
Platform: UNKNOWN
Classifier: Programming Language :: Python
Classifier: License :: OSI Approved :: MIT License
Classifier: Operating System :: OS Independent
Classifier: Topic :: Scientific/Engineering :: Physics
Requires-Dist: tensorflow (>=2)
Requires-Dist: scikit-learn (>=0.22)
Requires-Dist: uproot (>=3)
Requires-Dist: matplotlib (>=3)
Requires-Dist: numpy (>=1)
